bibliothecarius/__init__.py
bibliothecarius-0.0.1.dist-info/LICENSE
bibliothecarius-0.0.1.dist-info/METADATA
bibliothecarius-0.0.1.dist-info/WHEEL
bibliothecarius-0.0.1.dist-info/top_level.txt
bibliothecarius-0.0.1.dist-info/RECORD
